noisepy/functions_2019/S0B_to_ASDF_2019.py
noisepy/functions_2019/noise_module.py
noisepy/imaging/dispersion_analysis.py
noisepy/monitoring/attenuation_utils.py
noisepy/monitoring/monitoring_methods.py
noisepy/monitoring/monitoring_utils.py
noisepy/monitoring/plotting_attenuation.py
noisepy/seis/__init__.py
noisepy/seis/_version.py
noisepy/seis/constants.py
noisepy/seis/correlate.py
noisepy/seis/fdsn_download.py
noisepy/seis/main.py
noisepy/seis/noise_module.py
noisepy/seis/scheduler.py
noisepy/seis/stack.py
noisepy_seis-0.9.91.dist-info/METADATA
noisepy_seis-0.9.91.dist-info/WHEEL
noisepy_seis-0.9.91.dist-info/entry_points.txt
noisepy_seis-0.9.91.dist-info/licenses/LICENSE
noisepy_seis-0.9.91.dist-info/RECORD
