Metadata-Version: 2.4
Name: noisepy-seis
Version: 0.9.91
Summary: A High-performance Computing Python Package for Ambient Noise Analysis
Project-URL: Homepage, https://github.com/noisepy/NoisePy
Author-email: Marine Denolle <mdenolle@uw.edu>, Chengxin Jiang <Chengxin.Jiang1@anu.edu.au>, Yiyu Ni <niyiyu@uw.edu>
License: MIT License
License-File: LICENSE
Keywords: ambient,change,cross-correlation,dispersion,monitoring,noise,seismic,surface,velocity,wave
Classifier: Environment :: Console
Classifier: Intended Audience :: Developers
Classifier: Intended Audience :: Science/Research
Classifier: Operating System :: OS Independent
Classifier: Programming Language :: Python :: 3.10
Requires-Python: <3.11,>=3.9
Requires-Dist: aiobotocore==2.5.2
Requires-Dist: datetimerange<3.0.0,>=2.0.0
Requires-Dist: diskcache<6.0.0,>=5.6.1
Requires-Dist: fsspec<2024.0.0,>=2023.4.0
Requires-Dist: h5py<4.0.0,>=3.8.0
Requires-Dist: noisepy-seis-io>=0.3.0
Requires-Dist: numba<1.0.0,>=0.57.0
Requires-Dist: numpy<2.0.0,>=1.22.0
Requires-Dist: pandas<2.0.0,>=1.5.3
Requires-Dist: psutil<6.0.0,>=5.9.5
Requires-Dist: pyasdf<1.0.0,>=0.7.5
Requires-Dist: pycwt<1.0.0,>=0.3.0a22
Requires-Dist: pydantic-yaml==1.0
Requires-Dist: pydantic==2.3.0
Requires-Dist: pyyaml==6.0
Requires-Dist: s3fs<2024.0.0,==2023.4.0
Requires-Dist: scipy==1.12.0
Requires-Dist: zarr==2.14.2
Provides-Extra: aws
Requires-Dist: boto3<2.0.0,>=1.26.0; extra == 'aws'
Provides-Extra: dev
Requires-Dist: memory-profiler==0.61; extra == 'dev'
Requires-Dist: pre-commit==3.3.3; extra == 'dev'
Requires-Dist: pytest-cov==4.1.0; extra == 'dev'
Requires-Dist: pytest==7.2.2; extra == 'dev'
Provides-Extra: mpi
Requires-Dist: mpi4py<4.0.0,>=3.1.4; extra == 'mpi'
Provides-Extra: sql
Requires-Dist: sqlite3-0611; extra == 'sql'
